aplazame_sdk/__init__.py
aplazame_sdk-0.2.6.dist-info/DESCRIPTION.rst
aplazame_sdk-0.2.6.dist-info/METADATA
aplazame_sdk-0.2.6.dist-info/RECORD
aplazame_sdk-0.2.6.dist-info/WHEEL
aplazame_sdk-0.2.6.dist-info/dependency_links.txt
aplazame_sdk-0.2.6.dist-info/metadata.json
aplazame_sdk-0.2.6.dist-info/top_level.txt
