Metadata-Version: 2.0
Name: aplazame-sdk
Version: 0.2.6
Summary: Python SDK for Aplazame REST API
Home-page: https://github.com/aplazame/aplazame-sdk
Author: calvin
Author-email: dani@aplazame.com
License: Apache 2.0
Keywords: python,aplazame,api,rest,sdk
Platform: UNKNOWN
Classifier: Programming Language :: Python
Classifier: Natural Language :: English
Classifier: Intended Audience :: Developers
Classifier: License :: OSI Approved :: Apache Software License
Classifier: Operating System :: OS Independent
Classifier: Programming Language :: Python
Classifier: Programming Language :: Python :: 2.6
Classifier: Programming Language :: Python :: 2.7
Classifier: Programming Language :: Python :: 3
Classifier: Programming Language :: Python :: 3.3
Classifier: Programming Language :: Python :: 3.4
Requires-Dist: requests (>=1.1.0)
